<?xml version="1.0" encoding="UTF-8"?>
<!DOCTYPE mapper PUBLIC "-//mybatis.org//DTD Mapper 3.0//EN" "http://mybatis.org/dtd/mybatis-3-mapper.dtd">
<mapper namespace="com.eservice.api.dao.OrderSignMapper">
  <resultMap id="BaseResultMap" type="com.eservice.api.model.order_sign.OrderSign">
    <!--
      WARNING - @mbg.generated
    -->
    <id column="id" jdbcType="INTEGER" property="id" />
    <result column="order_id" jdbcType="INTEGER" property="orderId" />
    <result column="create_time" jdbcType="TIMESTAMP" property="createTime" />
    <result column="update_time" jdbcType="TIMESTAMP" property="updateTime" />
    <result column="sign_content" jdbcType="LONGVARCHAR" property="signContent" />
  </resultMap>

  <select id="getOrderSignListByContractId" resultMap="BaseResultMap">
    SELECT os.* from order_sign os
    JOIN machine_order mo on mo.id = os.order_id
    JOIN contract c on c.id = mo.contract_id
    WHERE c.id =  #{contractId}
  </select>
  
  <select id="getOrderSignListByOrderId" resultMap="BaseResultMap">
    SELECT os.*
    FROM order_sign os
    WHERE os.order_id = #{orderId}
  </select>
</mapper>